MANIFEST.in
README.md
setup.py
libmcleece/.git
libmcleece/.gitignore
libmcleece/.gitmodules
libmcleece/CMakeLists.txt
libmcleece/LICENSE
libmcleece/README.md
libmcleece/package-portable-linux.sh
libmcleece/.github/workflows/ci.yml
libmcleece/libsodium/.git
libmcleece/libsodium/.gitignore
libmcleece/libsodium/.gitmodules
libmcleece/libsodium/CMakeLists.txt
libmcleece/libsodium/LICENSE
libmcleece/libsodium/README.md
libmcleece/libsodium/.github/workflows/linux-ci.yaml
libmcleece/libsodium/.github/workflows/windows-ci.yaml
libmcleece/libsodium/libsodium/.git
libmcleece/libsodium/libsodium/.gitignore
libmcleece/libsodium/libsodium/.travis.yml
libmcleece/libsodium/libsodium/AUTHORS
libmcleece/libsodium/libsodium/ChangeLog
libmcleece/libsodium/libsodium/LICENSE
libmcleece/libsodium/libsodium/Makefile.am
libmcleece/libsodium/libsodium/README.markdown
libmcleece/libsodium/libsodium/THANKS
libmcleece/libsodium/libsodium/appveyor.yml
libmcleece/libsodium/libsodium/autogen.sh
libmcleece/libsodium/libsodium/azure-pipelines.yml
libmcleece/libsodium/libsodium/configure.ac
libmcleece/libsodium/libsodium/lgtm.yml
libmcleece/libsodium/libsodium/libsodium-uninstalled.pc.in
libmcleece/libsodium/libsodium/libsodium.pc.in
libmcleece/libsodium/libsodium/libsodium.sln
libmcleece/libsodium/libsodium/libsodium.vcxproj
libmcleece/libsodium/libsodium/libsodium.vcxproj.filters
libmcleece/libsodium/libsodium/logo.png
libmcleece/libsodium/libsodium/builds/.gitignore
libmcleece/libsodium/libsodium/builds/Makefile.am
libmcleece/libsodium/libsodium/builds/msvc/resource.h
libmcleece/libsodium/libsodium/builds/msvc/resource.rc
libmcleece/libsodium/libsodium/builds/msvc/version.h
libmcleece/libsodium/libsodium/builds/msvc/build/buildall.bat
libmcleece/libsodium/libsodium/builds/msvc/build/buildbase.bat
libmcleece/libsodium/libsodium/builds/msvc/properties/Common.props
libmcleece/libsodium/libsodium/builds/msvc/properties/DLL.props
libmcleece/libsodium/libsodium/builds/msvc/properties/Debug.props
mcleece.egg-info/PKG-INFO
mcleece.egg-info/SOURCES.txt
mcleece.egg-info/dependency_links.txt
mcleece.egg-info/not-zip-safe
mcleece.egg-info/requires.txt
mcleece.egg-info/top_level.txt