Metadata-Version: 2.1
Name: mcleece
Version: 0.4.0
Summary: Python wrapper for libmcleece encryption library
Home-page: https://github.com/sz3/pymcleece
Author: Stephen Zimmerman
Author-email: sz@recv.cc
License: MIT
Platform: UNKNOWN
Classifier: License :: OSI Approved :: MIT License
